starr/__init__.py
starr/_cython.cpython-36m-darwin.so
starr/sumtree_array.py
starr/experimental/__init__.py
starr/experimental/_cython.cpython-36m-darwin.so
starr/experimental/benchmarks.py
starr/experimental/slow.py
starr/experimental/src/_sumtree_array.pyx
starr/experimental/src/sumtree_array.cpp
starr/experimental/src/sumtree_array.h
starr/src/_sumtree_array.pyx
starr-0.3.2.dist-info/LICENSE
starr-0.3.2.dist-info/METADATA
starr-0.3.2.dist-info/WHEEL
starr-0.3.2.dist-info/top_level.txt
starr-0.3.2.dist-info/RECORD
