Metadata-Version: 2.1
Name: starr
Version: 0.3.2
Summary: Sumtrees for NumPy arrays
Home-page: https://github.com/justinmaojones/starr
Author: Justin Mao-Jones
Author-email: justinmaojones@gmail.com
License: MIT
Platform: UNKNOWN
Classifier: License :: OSI Approved :: MIT License
Classifier: Programming Language :: Python :: 3.7
Classifier: Programming Language :: Python :: 3.8
Classifier: Programming Language :: Python :: 3.9
License-File: LICENSE
Requires-Dist: numpy
Provides-Extra: dev
Requires-Dist: black ; extra == 'dev'
Requires-Dist: coverage ; extra == 'dev'
Requires-Dist: Cython ; extra == 'dev'
Requires-Dist: flake8 ; extra == 'dev'
Requires-Dist: numpy ; extra == 'dev'
Requires-Dist: pandas ; extra == 'dev'
Requires-Dist: pytest ; extra == 'dev'
Requires-Dist: tabulate ; extra == 'dev'
Requires-Dist: tox ; extra == 'dev'
Requires-Dist: twine ; extra == 'dev'
